flow/__init__.py
flow/autograd.py
flow/function.py
flow/module.py
flow/optim.py
flow/tensor.py
py_flow-0.0.2.dist-info/LICENSE
py_flow-0.0.2.dist-info/METADATA
py_flow-0.0.2.dist-info/WHEEL
py_flow-0.0.2.dist-info/top_level.txt
py_flow-0.0.2.dist-info/RECORD
