Metadata-Version: 2.1
Name: py-flow
Version: 0.0.2
Summary: Simple pytorch implementation
Home-page: https://github.com/Cjkkkk/Pyflow
Author: cjkkkk
Author-email: 656569648@qq.com
License: MIT
Platform: UNKNOWN
